{
  "Name": "Heliolite",
  "Inherits": "Wight",
  "Type": "Foe",
  "Chapter": 2,
  "RemoveActions": "Overpower",
  "Actions": [
    {
      "Name": "Redondo",
      "ActionCost": 0,
      "Description": "Swap places with an adjacent ally, removing and placing both characters."
    },
    {
      "Name": "Seeking Javelin",
      "ActionCost": 1,
      "Tags": [ "range 4", "true strike" ],
      "Hit": "[D]+[fray].",
      "Miss": "[fray].",
      "Effects": [
        "Foe is slashed.",
        "Has no maximum range and ignores cover against slashed foes."
      ]
    }
  ]
}