{
  "Name": "Necrosavant",
  "Inherits": "Relict",
  "Class": "Leader",
  "Vitality": 10,
  "Speed": 4,
  "Defense": 8,
  "FrayDamage": 3,
  "DamageDie": 6,
  "Traits": [ "Shelter", "Diaga" ],
  "Actions": [
    {
      "Name": "Unholy",
      "ActionCost": 1,
      "Tags": [ "ranged attack 6", "blast 1" ],
      "Hit": "[D]+[fray] and foe is branded.",
      "Miss": "[fray].",
      "AreaEffect": "[fray].",
      "Effect": "This action can also be made as a close blast 1 melee attack."
    },
    {
      "Name": "Fear",
      "ActionCost": 1,
      "Tags": [ "multimark", "repeatable" ],
      "Description": "Mark a foe in range 6. While marked, that foe gains +1 curse on attacks and saves unless adjacent to an ally. If they end their turn adjacent to an ally, they can pass a save to clear this mark."
    },
    {
      "Name": "Raise Dead",
      "ActionCost": 2,
      "Tags": [ "1/combat" ],
      "Description": "Restore a defeated Relict in range 6 to 50% hp and remove incapacitated."
    }
  ],
  "Chapter2": {
    "Actions": [
      {
        "Name": "Soul Shred",
        "ActionCost": 1,
        "Chapter": 2,
        "Recharge": 4,
        "Tags": [ "multimark" ],
        "Description": "Mark a foe in range 6. While marked, that foe gains Aura 1. Allies of that foe that end their turn in the aura take [fray] piercing damage."
      }
    ]
  },
  "Chapter3": {
    "Actions": [
      {
        "Name": "Radiance of the Black Sun",
        "ActionCost": 2,
        "Tags": [ "1/combat" ],
        "Description": "This character becomes immobile but gains Aura 2 until the start of its next turn. While the aura is active, Relict in the area cannot be reduced past 1 hp. This Aura also deactivates if this character is stunned."
      }
    ]
  }
}